moviebotapi/__init__.py
moviebotapi/amr.py
moviebotapi/auth.py
moviebotapi/common.py
moviebotapi/config.py
moviebotapi/douban.py
moviebotapi/downloader.py
moviebotapi/event.py
moviebotapi/ext.py
moviebotapi/library.py
moviebotapi/mediaserver.py
moviebotapi/meta.py
moviebotapi/notify.py
moviebotapi/plugin.py
moviebotapi/scraper.py
moviebotapi/site.py
moviebotapi/subscribe.py
moviebotapi/tmdb.py
moviebotapi/user.py
moviebotapi/core/__init__.py
moviebotapi/core/basemodel.py
moviebotapi/core/country_mapping.txt
moviebotapi/core/decorators.py
moviebotapi/core/exceptions.py
moviebotapi/core/models.py
moviebotapi/core/session.py
moviebotapi/core/utils.py
movie_bot_api-0.0.62.dist-info/LICENSE
movie_bot_api-0.0.62.dist-info/METADATA
movie_bot_api-0.0.62.dist-info/WHEEL
movie_bot_api-0.0.62.dist-info/top_level.txt
movie_bot_api-0.0.62.dist-info/RECORD
