Metadata-Version: 2.1
Name: movie-bot-api
Version: 0.0.62
Summary: 智能影音机器人MovieBot的接口SDK
Home-page: https://github.com/pofey/movie-bot-api
Author: yee
Author-email: yipengfei329@gmail.com
License: MIT
Keywords: movie bot,movie robot
Classifier: License :: OSI Approved :: MIT License
Classifier: Intended Audience :: Developers
Classifier: Natural Language :: Chinese (Simplified)
Classifier: Operating System :: OS Independent
Classifier: Programming Language :: Python :: 3.8
Classifier: Programming Language :: Python :: 3.9
Classifier: Programming Language :: Python :: 3.10
Classifier: Topic :: Internet
Classifier: Topic :: Software Development :: Libraries
Classifier: Topic :: Software Development :: Libraries :: Python Modules
Classifier: Topic :: Utilities
Requires-Python: >=3.8
License-File: LICENSE
Requires-Dist: httpx
Requires-Dist: pyrate-limiter
Requires-Dist: tenacity
Requires-Dist: cn2an
Requires-Dist: click
Requires-Dist: PyYAML
